json_to_sql/__init__.py
json_to_sql/schemas.py
json_to_sql/filters/__init__.py
json_to_sql/filters/filters.py
json_to_sql-0.1.9.dist-info/METADATA
json_to_sql-0.1.9.dist-info/WHEEL
json_to_sql-0.1.9.dist-info/top_level.txt
json_to_sql-0.1.9.dist-info/RECORD
