Metadata-Version: 2.1
Name: json_to_sql
Version: 0.1.9
Summary: A fast-api extension for creating standard resource searches
Home-page: https://github.com/koen199/fastapi-filter
Author: Van den Maegdenbergh Koen
Author-email: koen_vdm@hotmail.com
License: Creative Commons Attribution-Noncommercial-Share Alike license
Requires-Dist: sqlalchemy
Requires-Dist: pydantic
